{
  "aggregate": {
    "timestamp": "2021-03-08T17:16:54.581Z",
    "scenariosCreated": 720,
    "scenariosCompleted": 720,
    "requestsCompleted": 720,
    "latency": {
      "min": 278.8,
      "max": 1300.3,
      "median": 296.1,
      "p95": 336.7,
      "p99": 691.6
    },
    "rps": {
      "count": 720,
      "mean": 2
    },
    "scenarioDuration": {
      "min": 280.4,
      "max": 1302,
      "median": 298.6,
      "p95": 344.4,
      "p99": 694.9
    },
    "scenarioCounts": {
      "just get hash": 720
    },
    "errors": {},
    "codes": {
      "200": 720
    },
    "matches": 0,
    "customStats": {},
    "counters": {},
    "scenariosAvoided": 0,
    "phases": [
      {
        "duration": 360,
        "arrivalRate": 2,
        "name": "Warm up"
      }
    ]
  },
  "intermediate": [
    {
      "timestamp": "2021-03-08T17:11:04.052Z",
      "scenariosCreated": 19,
      "scenariosCompleted": 19,
      "requestsCompleted": 19,
      "latency": {
        "min": 288.9,
        "max": 313.1,
        "median": 295.6,
        "p95": 311.7,
        "p99": 313.1
      },
      "rps": {
        "count": 19,
        "mean": 2.01
      },
      "scenarioDuration": {
        "min": 291.8,
        "max": 343.2,
        "median": 299.8,
        "p95": 329.3,
        "p99": 343.2
      },
      "scenarioCounts": {
        "just get hash": 19
      },
      "errors": {},
      "codes": {
        "200": 19
      },
      "matches": 0,
      "latencies": [
        313136252,
        297372484,
        302842850,
        296313900,
        294298381,
        305944327,
        309851993,
        293308567,
        293355116,
        304471819,
        288891665,
        295555075,
        289607089,
        289659976,
        290434843,
        295513180,
        293982455,
        302842253,
        309127657
      ],
      "customStats": {},
      "counters": {},
      "concurrency": 0,
      "pendingRequests": 0,
      "scenariosAvoided": 0
    },
    {
      "timestamp": "2021-03-08T17:11:14.049Z",
      "scenariosCreated": 20,
      "scenariosCompleted": 20,
      "requestsCompleted": 20,
      "latency": {
        "min": 283.5,
        "max": 321.1,
        "median": 296.3,
        "p95": 318.7,
        "p99": 321.1
      },
      "rps": {
        "count": 20,
        "mean": 2
      },
      "scenarioDuration": {
        "min": 286.4,
        "max": 325,
        "median": 299.6,
        "p95": 324.5,
        "p99": 325
      },
      "scenarioCounts": {
        "just get hash": 20
      },
      "errors": {},
      "codes": {
        "200": 20
      },
      "matches": 0,
      "latencies": [
        316358144,
        295868073,
        306524658,
        297101892,
        287442743,
        291476475,
        303959685,
        307523070,
        283517205,
        289473065,
        311779055,
        305373276,
        290968732,
        308182192,
        291679360,
        294554509,
        321055194,
        296732858,
        292392375,
        290918965
      ],
      "customStats": {},
      "counters": {},
      "concurrency": 0,
      "pendingRequests": 0,
      "scenariosAvoided": 0
    },
    {
      "timestamp": "2021-03-08T17:11:24.049Z",
      "scenariosCreated": 20,
      "scenariosCompleted": 20,
      "requestsCompleted": 20,
      "latency": {
        "min": 287.1,
        "max": 348.7,
        "median": 296.7,
        "p95": 344.3,
        "p99": 348.7
      },
      "rps": {
        "count": 20,
        "mean": 2
      },
      "scenarioDuration": {
        "min": 289.7,
        "max": 350.7,
        "median": 299.9,
        "p95": 348.6,
        "p99": 350.7
      },
      "scenarioCounts": {
        "just get hash": 20
      },
      "errors": {},
      "codes": {
        "200": 20
      },
      "matches": 0,
      "latencies": [
        290533140,
        287066784,
        297904000,
        298314301,
        293355109,
        312528143,
        300467069,
        334718702,
        294763150,
        292329097,
        339856012,
        303474632,
        292430250,
        292882081,
        295568048,
        293131912,
        306593791,
        313489984,
        348698963,
        293867695
      ],
      "customStats": {},
      "counters": {},
      "concurrency": 0,
      "pendingRequests": 0,
      "scenariosAvoided": 0
    },
    {
      "timestamp": "2021-03-08T17:11:34.050Z",
      "scenariosCreated": 20,
      "scenariosCompleted": 20,
      "requestsCompleted": 20,
      "latency": {
        "min": 287.3,
        "max": 343.2,
        "median": 299.8,
        "p95": 342.4,
        "p99": 343.2
      },
      "rps": {
        "count": 20,
        "mean": 2
      },
      "scenarioDuration": {
        "min": 289.7,
        "max": 346.7,
        "median": 302.5,
        "p95": 346.1,
        "p99": 346.7
      },
      "scenarioCounts": {
        "just get hash": 20
      },
      "errors": {},
      "codes": {
        "200": 20
      },
      "matches": 0,
      "latencies": [
        295059575,
        292186257,
        287294635,
        317143960,
        289894050,
        290415509,
        293744168,
        301232123,
        304970977,
        291852262,
        304477361,
        308733632,
        301126017,
        305201590,
        298413431,
        292944646,
        343248111,
        295065626,
        302285076,
        341553140
      ],
      "customStats": {},
      "counters": {},
      "concurrency": 0,
      "pendingRequests": 0,
      "scenariosAvoided": 0
    },
    {
      "timestamp": "2021-03-08T17:11:44.050Z",
      "scenariosCreated": 20,
      "scenariosCompleted": 20,
      "requestsCompleted": 20,
      "latency": {
        "min": 290.2,
        "max": 379.8,
        "median": 294.2,
        "p95": 363.5,
        "p99": 379.8
      },
      "rps": {
        "count": 20,
        "mean": 2
      },
      "scenarioDuration": {
        "min": 292.6,
        "max": 382.6,
        "median": 298.8,
        "p95": 368.3,
        "p99": 382.6
      },
      "scenarioCounts": {
        "just get hash": 20
      },
      "errors": {},
      "codes": {
        "200": 20
      },
      "matches": 0,
      "latencies": [
        343383086,
        291210962,
        297615498,
        292122026,
        296073898,
        346954122,
        295618804,
        291161071,
        313636521,
        379814653,
        290172105,
        305596480,
        347159558,
        294248937,
        292020947,
        292812284,
        292219311,
        294160508,
        290347750,
        290244509
      ],
      "customStats": {},
      "counters": {},
      "concurrency": 0,
      "pendingRequests": 0,
      "scenariosAvoided": 0
    },
    {
      "timestamp": "2021-03-08T17:11:54.049Z",
      "scenariosCreated": 20,
      "scenariosCompleted": 20,
      "requestsCompleted": 20,
      "latency": {
        "min": 290.3,
        "max": 819.7,
        "median": 294.7,
        "p95": 814.3,
        "p99": 819.7
      },
      "rps": {
        "count": 20,
        "mean": 2
      },
      "scenarioDuration": {
        "min": 293.4,
        "max": 826,
        "median": 297.7,
        "p95": 819.2,
        "p99": 826
      },
      "scenarioCounts": {
        "just get hash": 20
      },
      "errors": {},
      "codes": {
        "200": 20
      },
      "matches": 0,
      "latencies": [
        305482517,
        303387705,
        294898094,
        293547721,
        291406948,
        306051321,
        296414203,
        808931181,
        310440313,
        294146717,
        292288776,
        347560172,
        293733163,
        293694241,
        292699425,
        292991388,
        819722178,
        320159551,
        294579627,
        290293583
      ],
      "customStats": {},
      "counters": {},
      "concurrency": 0,
      "pendingRequests": 0,
      "scenariosAvoided": 0
    },
    {
      "timestamp": "2021-03-08T17:12:04.051Z",
      "scenariosCreated": 20,
      "scenariosCompleted": 20,
      "requestsCompleted": 20,
      "latency": {
        "min": 286.8,
        "max": 312,
        "median": 295.5,
        "p95": 309.1,
        "p99": 312
      },
      "rps": {
        "count": 20,
        "mean": 2
      },
      "scenarioDuration": {
        "min": 289.3,
        "max": 315.1,
        "median": 299.1,
        "p95": 311.7,
        "p99": 315.1
      },
      "scenarioCounts": {
        "just get hash": 20
      },
      "errors": {},
      "codes": {
        "200": 20
      },
      "matches": 0,
      "latencies": [
        294931456,
        294888575,
        298200526,
        302110455,
        288330760,
        291526028,
        295691836,
        304093143,
        297797635,
        294174096,
        306183833,
        295388052,
        286771116,
        300990576,
        295984655,
        311976941,
        287630269,
        294258973,
        304350607,
        294969541
      ],
      "customStats": {},
      "counters": {},
      "concurrency": 0,
      "pendingRequests": 0,
      "scenariosAvoided": 0
    },
    {
      "timestamp": "2021-03-08T17:12:14.050Z",
      "scenariosCreated": 20,
      "scenariosCompleted": 20,
      "requestsCompleted": 20,
      "latency": {
        "min": 283.1,
        "max": 306,
        "median": 292.7,
        "p95": 305.5,
        "p99": 306
      },
      "rps": {
        "count": 20,
        "mean": 2
      },
      "scenarioDuration": {
        "min": 285.8,
        "max": 308.2,
        "median": 295.3,
        "p95": 308,
        "p99": 308.2
      },
      "scenarioCounts": {
        "just get hash": 20
      },
      "errors": {},
      "codes": {
        "200": 20
      },
      "matches": 0,
      "latencies": [
        283112075,
        290866303,
        286925241,
        299312673,
        295044648,
        293007444,
        295437942,
        286026868,
        292213405,
        291518907,
        304894268,
        306017565,
        295395139,
        292283763,
        297974383,
        301845162,
        283090662,
        295880920,
        292484319,
        288168973
      ],
      "customStats": {},
      "counters": {},
      "concurrency": 0,
      "pendingRequests": 0,
      "scenariosAvoided": 0
    },
    {
      "timestamp": "2021-03-08T17:12:24.051Z",
      "scenariosCreated": 20,
      "scenariosCompleted": 20,
      "requestsCompleted": 20,
      "latency": {
        "min": 281.9,
        "max": 322.8,
        "median": 307.7,
        "p95": 322.6,
        "p99": 322.8
      },
      "rps": {
        "count": 20,
        "mean": 2
      },
      "scenarioDuration": {
        "min": 284,
        "max": 325,
        "median": 310.5,
        "p95": 324.7,
        "p99": 325
      },
      "scenarioCounts": {
        "just get hash": 20
      },
      "errors": {},
      "codes": {
        "200": 20
      },
      "matches": 0,
      "latencies": [
        292150859,
        296495800,
        320475909,
        301676651,
        281940407,
        319795200,
        308504585,
        283545205,
        306964190,
        293338967,
        312705328,
        318210379,
        297902822,
        314489604,
        311183815,
        322336763,
        295443068,
        312586478,
        296823997,
        322839066
      ],
      "customStats": {},
      "counters": {},
      "concurrency": 0,
      "pendingRequests": 0,
      "scenariosAvoided": 0
    },
    {
      "timestamp": "2021-03-08T17:12:34.053Z",
      "scenariosCreated": 20,
      "scenariosCompleted": 20,
      "requestsCompleted": 20,
      "latency": {
        "min": 281.8,
        "max": 318.2,
        "median": 297.2,
        "p95": 316.5,
        "p99": 318.2
      },
      "rps": {
        "count": 20,
        "mean": 2
      },
      "scenarioDuration": {
        "min": 283.6,
        "max": 320.3,
        "median": 299.7,
        "p95": 319.4,
        "p99": 320.3
      },
      "scenarioCounts": {
        "just get hash": 20
      },
      "errors": {},
      "codes": {
        "200": 20
      },
      "matches": 0,
      "latencies": [
        288794387,
        293674701,
        318212558,
        304445202,
        307159410,
        284073042,
        314794120,
        304955788,
        289329897,
        297628303,
        301766098,
        304122489,
        281793705,
        298910373,
        301589051,
        290053522,
        291212200,
        296747452,
        289717769,
        294849128
      ],
      "customStats": {},
      "counters": {},
      "concurrency": 0,
      "pendingRequests": 0,
      "scenariosAvoided": 0
    },
    {
      "timestamp": "2021-03-08T17:12:44.056Z",
      "scenariosCreated": 20,
      "scenariosCompleted": 20,
      "requestsCompleted": 20,
      "latency": {
        "min": 286,
        "max": 322.8,
        "median": 298.1,
        "p95": 320.2,
        "p99": 322.8
      },
      "rps": {
        "count": 20,
        "mean": 2
      },
      "scenarioDuration": {
        "min": 287.9,
        "max": 324.5,
        "median": 300.2,
        "p95": 322,
        "p99": 324.5
      },
      "scenarioCounts": {
        "just get hash": 20
      },
      "errors": {},
      "codes": {
        "200": 20
      },
      "matches": 0,
      "latencies": [
        285984773,
        303917934,
        289934042,
        309833688,
        298062893,
        293187103,
        293819082,
        302621652,
        294966598,
        306518219,
        309681768,
        291106294,
        297886103,
        288463820,
        299423220,
        294659093,
        307716982,
        322833802,
        317502881,
        298211883
      ],
      "customStats": {},
      "counters": {},
      "concurrency": 0,
      "pendingRequests": 0,
      "scenariosAvoided": 0
    },
    {
      "timestamp": "2021-03-08T17:12:54.058Z",
      "scenariosCreated": 20,
      "scenariosCompleted": 20,
      "requestsCompleted": 20,
      "latency": {
        "min": 284.2,
        "max": 359,
        "median": 302.4,
        "p95": 342.9,
        "p99": 359
      },
      "rps": {
        "count": 20,
        "mean": 2
      },
      "scenarioDuration": {
        "min": 286.7,
        "max": 361.3,
        "median": 304.4,
        "p95": 345.3,
        "p99": 361.3
      },
      "scenarioCounts": {
        "just get hash": 20
      },
      "errors": {},
      "codes": {
        "200": 20
      },
      "matches": 0,
      "latencies": [
        359042074,
        326690971,
        313183901,
        307554411,
        295439784,
        300104938,
        300892302,
        291875727,
        312438814,
        298809995,
        315994084,
        284219720,
        291364832,
        296295569,
        308928376,
        284271278,
        303824800,
        307570325,
        310469485,
        293000917
      ],
      "customStats": {},
      "counters": {},
      "concurrency": 0,
      "pendingRequests": 0,
      "scenariosAvoided": 0
    },
    {
      "timestamp": "2021-03-08T17:13:04.058Z",
      "scenariosCreated": 20,
      "scenariosCompleted": 20,
      "requestsCompleted": 20,
      "latency": {
        "min": 284.3,
        "max": 326.2,
        "median": 303,
        "p95": 321.5,
        "p99": 326.2
      },
      "rps": {
        "count": 20,
        "mean": 2
      },
      "scenarioDuration": {
        "min": 286.5,
        "max": 328.3,
        "median": 305.1,
        "p95": 323.9,
        "p99": 328.3
      },
      "scenarioCounts": {
        "just get hash": 20
      },
      "errors": {},
      "codes": {
        "200": 20
      },
      "matches": 0,
      "latencies": [
        293268298,
        296085948,
        311382160,
        284279614,
        295443383,
        304626953,
        299309296,
        293696432,
        313362731,
        306853678,
        297482724,
        315727017,
        304319241,
        298839719,
        316787742,
        301910485,
        326224258,
        302153622,
        311517917,
        303824697
      ],
      "customStats": {},
      "counters": {},
      "concurrency": 0,
      "pendingRequests": 0,
      "scenariosAvoided": 0
    },
    {
      "timestamp": "2021-03-08T17:13:14.061Z",
      "scenariosCreated": 20,
      "scenariosCompleted": 20,
      "requestsCompleted": 20,
      "latency": {
        "min": 294.1,
        "max": 344.3,
        "median": 315.6,
        "p95": 341.5,
        "p99": 344.3
      },
      "rps": {
        "count": 20,
        "mean": 2
      },
      "scenarioDuration": {
        "min": 295.7,
        "max": 364.2,
        "median": 318.6,
        "p95": 355.3,
        "p99": 364.2
      },
      "scenarioCounts": {
        "just get hash": 20
      },
      "errors": {},
      "codes": {
        "200": 20
      },
      "matches": 0,
      "latencies": [
        318241268,
        316883342,
        294133852,
        302822355,
        303978433,
        317439542,
        302150302,
        297953668,
        332351898,
        324743660,
        311357797,
        312061579,
        306035334,
        315893340,
        319928142,
        344301823,
        315324756,
        329940782,
        338615663,
        299536280
      ],
      "customStats": {},
      "counters": {},
      "concurrency": 0,
      "pendingRequests": 0,
      "scenariosAvoided": 0
    },
    {
      "timestamp": "2021-03-08T17:13:24.060Z",
      "scenariosCreated": 20,
      "scenariosCompleted": 20,
      "requestsCompleted": 20,
      "latency": {
        "min": 284.6,
        "max": 329.7,
        "median": 299.2,
        "p95": 327,
        "p99": 329.7
      },
      "rps": {
        "count": 20,
        "mean": 2
      },
      "scenarioDuration": {
        "min": 287.2,
        "max": 331.5,
        "median": 301.8,
        "p95": 329.2,
        "p99": 331.5
      },
      "scenarioCounts": {
        "just get hash": 20
      },
      "errors": {},
      "codes": {
        "200": 20
      },
      "matches": 0,
      "latencies": [
        324015284,
        329662188,
        324340918,
        314708793,
        319762576,
        309366201,
        310157459,
        284616576,
        296145002,
        301312377,
        297388974,
        299760522,
        291641257,
        298320174,
        298679459,
        298423092,
        289922258,
        295225844,
        306147043,
        292888309
      ],
      "customStats": {},
      "counters": {},
      "concurrency": 0,
      "pendingRequests": 0,
      "scenariosAvoided": 0
    },
    {
      "timestamp": "2021-03-08T17:13:34.060Z",
      "scenariosCreated": 20,
      "scenariosCompleted": 19,
      "requestsCompleted": 19,
      "latency": {
        "min": 285.1,
        "max": 845,
        "median": 296.3,
        "p95": 828.8,
        "p99": 845
      },
      "rps": {
        "count": 20,
        "mean": 2
      },
      "scenarioDuration": {
        "min": 287.7,
        "max": 846.9,
        "median": 298.7,
        "p95": 831.4,
        "p99": 846.9
      },
      "scenarioCounts": {
        "just get hash": 20
      },
      "errors": {},
      "codes": {
        "200": 19
      },
      "matches": 0,
      "latencies": [
        291110473,
        295562117,
        288979905,
        296289275,
        303667926,
        285149680,
        324789768,
        288344396,
        289027419,
        291251200,
        285080478,
        296909754,
        295688487,
        296650719,
        328115688,
        305469183,
        774227360,
        808978924,
        844965395
      ],
      "customStats": {},
      "counters": {},
      "concurrency": 1,
      "pendingRequests": 1,
      "scenariosAvoided": 0
    },
    {
      "timestamp": "2021-03-08T17:13:44.060Z",
      "scenariosCreated": 20,
      "scenariosCompleted": 21,
      "requestsCompleted": 21,
      "latency": {
        "min": 278.8,
        "max": 793.9,
        "median": 343.6,
        "p95": 639.5,
        "p99": 793.9
      },
      "rps": {
        "count": 20,
        "mean": 2
      },
      "scenarioDuration": {
        "min": 280.4,
        "max": 796.1,
        "median": 345.8,
        "p95": 641.6,
        "p99": 796.1
      },
      "scenarioCounts": {
        "just get hash": 20
      },
      "errors": {},
      "codes": {
        "200": 21
      },
      "matches": 0,
      "latencies": [
        793876753,
        300558162,
        323078725,
        343582429,
        366418378,
        390780056,
        414754170,
        439698085,
        463794698,
        488587299,
        513250081,
        321641857,
        285168448,
        348419590,
        295811727,
        406530034,
        295523526,
        284389659,
        295545497,
        289107707,
        278823044
      ],
      "customStats": {},
      "counters": {},
      "concurrency": 0,
      "pendingRequests": 0,
      "scenariosAvoided": 0
    },
    {
      "timestamp": "2021-03-08T17:13:54.060Z",
      "scenariosCreated": 20,
      "scenariosCompleted": 20,
      "requestsCompleted": 20,
      "latency": {
        "min": 281.3,
        "max": 304.7,
        "median": 295.2,
        "p95": 304,
        "p99": 304.7
      },
      "rps": {
        "count": 20,
        "mean": 2
      },
      "scenarioDuration": {
        "min": 283,
        "max": 306.3,
        "median": 297.2,
        "p95": 305.9,
        "p99": 306.3
      },
      "scenarioCounts": {
        "just get hash": 20
      },
      "errors": {},
      "codes": {
        "200": 20
      },
      "matches": 0,
      "latencies": [
        295830183,
        291606011,
        297570435,
        301439493,
        295584222,
        291810192,
        294335677,
        300847957,
        281311730,
        292106093,
        283335864,
        292783275,
        294855473,
        293346873,
        298019413,
        304668589,
        303282174,
        290172344,
        296522658,
        295826464
      ],
      "customStats": {},
      "counters": {},
      "concurrency": 0,
      "pendingRequests": 0,
      "scenariosAvoided": 0
    },
    {
      "timestamp": "2021-03-08T17:14:04.060Z",
      "scenariosCreated": 20,
      "scenariosCompleted": 20,
      "requestsCompleted": 20,
      "latency": {
        "min": 284.3,
        "max": 306.4,
        "median": 294.9,
        "p95": 306.1,
        "p99": 306.4
      },
      "rps": {
        "count": 20,
        "mean": 2
      },
      "scenarioDuration": {
        "min": 286.1,
        "max": 308.1,
        "median": 296.7,
        "p95": 307.8,
        "p99": 308.1
      },
      "scenarioCounts": {
        "just get hash": 20
      },
      "errors": {},
      "codes": {
        "200": 20
      },
      "matches": 0,
      "latencies": [
        292003704,
        290978003,
        298933631,
        298665934,
        295583871,
        303671977,
        294258613,
        287647079,
        296744456,
        291705715,
        291759663,
        284263484,
        305787113,
        292795392,
        300634634,
        291685535,
        300936160,
        297920200,
        306406066,
        290337058
      ],
      "customStats": {},
      "counters": {},
      "concurrency": 0,
      "pendingRequests": 0,
      "scenariosAvoided": 0
    },
    {
      "timestamp": "2021-03-08T17:14:14.060Z",
      "scenariosCreated": 20,
      "scenariosCompleted": 20,
      "requestsCompleted": 20,
      "latency": {
        "min": 287.3,
        "max": 319.8,
        "median": 295.5,
        "p95": 315.1,
        "p99": 319.8
      },
      "rps": {
        "count": 20,
        "mean": 2
      },
      "scenarioDuration": {
        "min": 288.9,
        "max": 321.6,
        "median": 297.2,
        "p95": 317,
        "p99": 321.6
      },
      "scenarioCounts": {
        "just get hash": 20
      },
      "errors": {},
      "codes": {
        "200": 20
      },
      "matches": 0,
      "latencies": [
        298640866,
        310363264,
        295226150,
        287301726,
        319788449,
        292190079,
        291041427,
        292488435,
        295804031,
        294925689,
        298439454,
        309846833,
        294788128,
        304554203,
        297227102,
        294144092,
        301849275,
        293076990,
        295914492,
        293032412
      ],
      "customStats": {},
      "counters": {},
      "concurrency": 0,
      "pendingRequests": 0,
      "scenariosAvoided": 0
    },
    {
      "timestamp": "2021-03-08T17:14:24.060Z",
      "scenariosCreated": 20,
      "scenariosCompleted": 20,
      "requestsCompleted": 20,
      "latency": {
        "min": 282.5,
        "max": 324.8,
        "median": 292.2,
        "p95": 313,
        "p99": 324.8
      },
      "rps": {
        "count": 20,
        "mean": 2
      },
      "scenarioDuration": {
        "min": 284.2,
        "max": 327,
        "median": 294,
        "p95": 315,
        "p99": 327
      },
      "scenarioCounts": {
        "just get hash": 20
      },
      "errors": {},
      "codes": {
        "200": 20
      },
      "matches": 0,
      "latencies": [
        284474395,
        298672793,
        294410230,
        291237301,
        286111335,
        295480421,
        292801890,
        301156943,
        286151672,
        290519404,
        291652105,
        289989565,
        291123915,
        282505704,
        295262198,
        324800745,
        296885417,
        289978665,
        299728807,
        293776038
      ],
      "customStats": {},
      "counters": {},
      "concurrency": 0,
      "pendingRequests": 0,
      "scenariosAvoided": 0
    },
    {
      "timestamp": "2021-03-08T17:14:34.060Z",
      "scenariosCreated": 20,
      "scenariosCompleted": 20,
      "requestsCompleted": 20,
      "latency": {
        "min": 279.1,
        "max": 304.7,
        "median": 294.2,
        "p95": 304.3,
        "p99": 304.7
      },
      "rps": {
        "count": 20,
        "mean": 2
      },
      "scenarioDuration": {
        "min": 280.7,
        "max": 306.9,
        "median": 295.9,
        "p95": 306.3,
        "p99": 306.9
      },
      "scenarioCounts": {
        "just get hash": 20
      },
      "errors": {},
      "codes": {
        "200": 20
      },
      "matches": 0,
      "latencies": [
        300890594,
        290785095,
        292006842,
        296789032,
        302809669,
        304652027,
        303889788,
        302843684,
        301942889,
        286974974,
        291842310,
        296775238,
        285924371,
        294205792,
        293323458,
        279053357,
        294200972,
        302754300,
        288910513,
        282648599
      ],
      "customStats": {},
      "counters": {},
      "concurrency": 0,
      "pendingRequests": 0,
      "scenariosAvoided": 0
    },
    {
      "timestamp": "2021-03-08T17:14:44.060Z",
      "scenariosCreated": 20,
      "scenariosCompleted": 19,
      "requestsCompleted": 19,
      "latency": {
        "min": 281.3,
        "max": 612.8,
        "median": 293.4,
        "p95": 607.3,
        "p99": 612.8
      },
      "rps": {
        "count": 20,
        "mean": 2
      },
      "scenarioDuration": {
        "min": 283,
        "max": 614.7,
        "median": 295.3,
        "p95": 609.2,
        "p99": 614.7
      },
      "scenarioCounts": {
        "just get hash": 20
      },
      "errors": {},
      "codes": {
        "200": 19
      },
      "matches": 0,
      "latencies": [
        293410154,
        308440691,
        288033945,
        294902827,
        290680408,
        281263204,
        291176117,
        288808829,
        286678124,
        285360617,
        303535702,
        298975977,
        289682849,
        284702979,
        528701855,
        393621221,
        560889938,
        600652741,
        612761579
      ],
      "customStats": {},
      "counters": {},
      "concurrency": 1,
      "pendingRequests": 1,
      "scenariosAvoided": 0
    },
    {
      "timestamp": "2021-03-08T17:14:54.060Z",
      "scenariosCreated": 20,
      "scenariosCompleted": 21,
      "requestsCompleted": 21,
      "latency": {
        "min": 285.2,
        "max": 1300.3,
        "median": 296.3,
        "p95": 946,
        "p99": 1300.3
      },
      "rps": {
        "count": 20,
        "mean": 2
      },
      "scenarioDuration": {
        "min": 286.9,
        "max": 1302,
        "median": 298.1,
        "p95": 947.7,
        "p99": 1302
      },
      "scenarioCounts": {
        "just get hash": 20
      },
      "errors": {},
      "codes": {
        "200": 21
      },
      "matches": 0,
      "latencies": [
        656151506,
        407711384,
        296990481,
        1300298874,
        292938361,
        286847785,
        287647817,
        286199150,
        296271520,
        301910123,
        300610393,
        289316097,
        298841022,
        292079797,
        292356485,
        286184472,
        292518990,
        303715803,
        285168216,
        299389496,
        301302799
      ],
      "customStats": {},
      "counters": {},
      "concurrency": 0,
      "pendingRequests": 0,
      "scenariosAvoided": 0
    },
    {
      "timestamp": "2021-03-08T17:15:04.060Z",
      "scenariosCreated": 20,
      "scenariosCompleted": 20,
      "requestsCompleted": 20,
      "latency": {
        "min": 282.3,
        "max": 308.7,
        "median": 292.1,
        "p95": 307.6,
        "p99": 308.7
      },
      "rps": {
        "count": 20,
        "mean": 2
      },
      "scenarioDuration": {
        "min": 284,
        "max": 312.4,
        "median": 293.8,
        "p95": 310.2,
        "p99": 312.4
      },
      "scenarioCounts": {
        "just get hash": 20
      },
      "errors": {},
      "codes": {
        "200": 20
      },
      "matches": 0,
      "latencies": [
        293273904,
        291212910,
        289332691,
        290372503,
        287453201,
        292380265,
        301653414,
        296308865,
        305994712,
        291781518,
        291213592,
        288068776,
        306466806,
        300131824,
        282310266,
        292520726,
        285714769,
        297717659,
        286282473,
        308711208
      ],
      "customStats": {},
      "counters": {},
      "concurrency": 0,
      "pendingRequests": 0,
      "scenariosAvoided": 0
    },
    {
      "timestamp": "2021-03-08T17:15:14.060Z",
      "scenariosCreated": 20,
      "scenariosCompleted": 20,
      "requestsCompleted": 20,
      "latency": {
        "min": 281.3,
        "max": 308.3,
        "median": 293.9,
        "p95": 308,
        "p99": 308.3
      },
      "rps": {
        "count": 20,
        "mean": 2
      },
      "scenarioDuration": {
        "min": 283.5,
        "max": 310.1,
        "median": 295.6,
        "p95": 309.8,
        "p99": 310.1
      },
      "scenarioCounts": {
        "just get hash": 20
      },
      "errors": {},
      "codes": {
        "200": 20
      },
      "matches": 0,
      "latencies": [
        288790023,
        301993187,
        292428294,
        302351360,
        308297889,
        290354208,
        307652866,
        296289549,
        293807048,
        303562706,
        288253990,
        290025906,
        292240079,
        294068768,
        306114038,
        281327288,
        293559141,
        290496441,
        307087231,
        294541664
      ],
      "customStats": {},
      "counters": {},
      "concurrency": 0,
      "pendingRequests": 0,
      "scenariosAvoided": 0
    },
    {
      "timestamp": "2021-03-08T17:15:24.061Z",
      "scenariosCreated": 20,
      "scenariosCompleted": 20,
      "requestsCompleted": 20,
      "latency": {
        "min": 285.3,
        "max": 316.1,
        "median": 296.9,
        "p95": 311.6,
        "p99": 316.1
      },
      "rps": {
        "count": 20,
        "mean": 2
      },
      "scenarioDuration": {
        "min": 287.2,
        "max": 317.9,
        "median": 298.7,
        "p95": 313.3,
        "p99": 317.9
      },
      "scenarioCounts": {
        "just get hash": 20
      },
      "errors": {},
      "codes": {
        "200": 20
      },
      "matches": 0,
      "latencies": [
        291429019,
        316058196,
        296914247,
        293228528,
        290491624,
        307113016,
        301103176,
        291077029,
        285282270,
        302509170,
        303750206,
        303207040,
        291667729,
        304044582,
        297567011,
        301790608,
        294930028,
        296918690,
        295759395,
        290247834
      ],
      "customStats": {},
      "counters": {},
      "concurrency": 0,
      "pendingRequests": 0,
      "scenariosAvoided": 0
    },
    {
      "timestamp": "2021-03-08T17:15:34.061Z",
      "scenariosCreated": 20,
      "scenariosCompleted": 20,
      "requestsCompleted": 20,
      "latency": {
        "min": 279.8,
        "max": 330.6,
        "median": 290.7,
        "p95": 330.4,
        "p99": 330.6
      },
      "rps": {
        "count": 20,
        "mean": 2
      },
      "scenarioDuration": {
        "min": 281.7,
        "max": 333,
        "median": 293,
        "p95": 332.3,
        "p99": 333
      },
      "scenarioCounts": {
        "just get hash": 20
      },
      "errors": {},
      "codes": {
        "200": 20
      },
      "matches": 0,
      "latencies": [
        279815635,
        298504857,
        286603903,
        291163065,
        302060706,
        287860541,
        317457355,
        297032092,
        328985631,
        290277682,
        280913492,
        330622473,
        285449997,
        281243370,
        330100168,
        290008648,
        281477333,
        311641070,
        288090041,
        295337565
      ],
      "customStats": {},
      "counters": {},
      "concurrency": 0,
      "pendingRequests": 0,
      "scenariosAvoided": 0
    },
    {
      "timestamp": "2021-03-08T17:15:44.061Z",
      "scenariosCreated": 20,
      "scenariosCompleted": 20,
      "requestsCompleted": 20,
      "latency": {
        "min": 284.8,
        "max": 301.5,
        "median": 293.6,
        "p95": 301.3,
        "p99": 301.5
      },
      "rps": {
        "count": 20,
        "mean": 2
      },
      "scenarioDuration": {
        "min": 287.7,
        "max": 304.2,
        "median": 295.5,
        "p95": 303.9,
        "p99": 304.2
      },
      "scenarioCounts": {
        "just get hash": 20
      },
      "errors": {},
      "codes": {
        "200": 20
      },
      "matches": 0,
      "latencies": [
        294022141,
        289848811,
        299690863,
        295711538,
        290859423,
        291098046,
        284843761,
        296430111,
        290514060,
        286246247,
        293645981,
        299580081,
        293578986,
        286816817,
        292745412,
        294437199,
        301173849,
        286221874,
        299786840,
        301512384
      ],
      "customStats": {},
      "counters": {},
      "concurrency": 0,
      "pendingRequests": 0,
      "scenariosAvoided": 0
    },
    {
      "timestamp": "2021-03-08T17:15:54.061Z",
      "scenariosCreated": 20,
      "scenariosCompleted": 20,
      "requestsCompleted": 20,
      "latency": {
        "min": 285.9,
        "max": 310,
        "median": 295.3,
        "p95": 308.9,
        "p99": 310
      },
      "rps": {
        "count": 20,
        "mean": 2
      },
      "scenarioDuration": {
        "min": 287.8,
        "max": 312.5,
        "median": 297.3,
        "p95": 310.9,
        "p99": 312.5
      },
      "scenarioCounts": {
        "just get hash": 20
      },
      "errors": {},
      "codes": {
        "200": 20
      },
      "matches": 0,
      "latencies": [
        293752178,
        297244834,
        287832516,
        295052374,
        309987477,
        307751208,
        292532016,
        290553476,
        295483389,
        285920518,
        296145449,
        299129793,
        294645194,
        301405892,
        296440198,
        302743164,
        292753902,
        287446017,
        294736663,
        299210221
      ],
      "customStats": {},
      "counters": {},
      "concurrency": 0,
      "pendingRequests": 0,
      "scenariosAvoided": 0
    },
    {
      "timestamp": "2021-03-08T17:16:04.061Z",
      "scenariosCreated": 20,
      "scenariosCompleted": 20,
      "requestsCompleted": 20,
      "latency": {
        "min": 285.4,
        "max": 310.1,
        "median": 298.5,
        "p95": 309.7,
        "p99": 310.1
      },
      "rps": {
        "count": 20,
        "mean": 2
      },
      "scenarioDuration": {
        "min": 287.5,
        "max": 311.9,
        "median": 300.6,
        "p95": 311.6,
        "p99": 311.9
      },
      "scenarioCounts": {
        "just get hash": 20
      },
      "errors": {},
      "codes": {
        "200": 20
      },
      "matches": 0,
      "latencies": [
        299320685,
        294087096,
        298669629,
        299658934,
        298371556,
        303807722,
        295038931,
        301219601,
        302025991,
        294887323,
        293835910,
        309223041,
        301784611,
        294335670,
        310119271,
        285379892,
        295522437,
        298273479,
        308255601,
        289095860
      ],
      "customStats": {},
      "counters": {},
      "concurrency": 0,
      "pendingRequests": 0,
      "scenariosAvoided": 0
    },
    {
      "timestamp": "2021-03-08T17:16:14.061Z",
      "scenariosCreated": 20,
      "scenariosCompleted": 20,
      "requestsCompleted": 20,
      "latency": {
        "min": 287.7,
        "max": 319.3,
        "median": 300.3,
        "p95": 318.8,
        "p99": 319.3
      },
      "rps": {
        "count": 20,
        "mean": 2
      },
      "scenarioDuration": {
        "min": 289.5,
        "max": 321.3,
        "median": 302.2,
        "p95": 320.6,
        "p99": 321.3
      },
      "scenarioCounts": {
        "just get hash": 20
      },
      "errors": {},
      "codes": {
        "200": 20
      },
      "matches": 0,
      "latencies": [
        302949308,
        296604526,
        296230459,
        291048846,
        290563438,
        295571278,
        310930406,
        287686097,
        314938771,
        293019610,
        297894443,
        319327065,
        300855493,
        306885252,
        293050751,
        309195434,
        307290880,
        305709064,
        318360389,
        299678541
      ],
      "customStats": {},
      "counters": {},
      "concurrency": 0,
      "pendingRequests": 0,
      "scenariosAvoided": 0
    },
    {
      "timestamp": "2021-03-08T17:16:24.061Z",
      "scenariosCreated": 20,
      "scenariosCompleted": 20,
      "requestsCompleted": 20,
      "latency": {
        "min": 287.1,
        "max": 325.5,
        "median": 294.6,
        "p95": 324.3,
        "p99": 325.5
      },
      "rps": {
        "count": 20,
        "mean": 2
      },
      "scenarioDuration": {
        "min": 288.9,
        "max": 327.4,
        "median": 296.4,
        "p95": 326.3,
        "p99": 327.4
      },
      "scenarioCounts": {
        "just get hash": 20
      },
      "errors": {},
      "codes": {
        "200": 20
      },
      "matches": 0,
      "latencies": [
        293098834,
        323071795,
        289548378,
        290319731,
        288143711,
        318492467,
        305056375,
        291255270,
        319088107,
        310622898,
        290217698,
        298408392,
        325531492,
        309692659,
        292290102,
        287121180,
        296178720,
        292752052,
        305334650,
        290035331
      ],
      "customStats": {},
      "counters": {},
      "concurrency": 0,
      "pendingRequests": 0,
      "scenariosAvoided": 0
    },
    {
      "timestamp": "2021-03-08T17:16:34.062Z",
      "scenariosCreated": 20,
      "scenariosCompleted": 20,
      "requestsCompleted": 20,
      "latency": {
        "min": 280.5,
        "max": 308.8,
        "median": 291.6,
        "p95": 308.4,
        "p99": 308.8
      },
      "rps": {
        "count": 20,
        "mean": 2
      },
      "scenarioDuration": {
        "min": 282.3,
        "max": 310.7,
        "median": 293.5,
        "p95": 310.2,
        "p99": 310.7
      },
      "scenarioCounts": {
        "just get hash": 20
      },
      "errors": {},
      "codes": {
        "200": 20
      },
      "matches": 0,
      "latencies": [
        286431775,
        308808683,
        296065766,
        298218682,
        308071870,
        284785873,
        304468833,
        291140183,
        280451161,
        289341598,
        287619908,
        292033656,
        285760757,
        284397480,
        306132837,
        297944582,
        284588061,
        297124780,
        294081247,
        282876026
      ],
      "customStats": {},
      "counters": {},
      "concurrency": 0,
      "pendingRequests": 0,
      "scenariosAvoided": 0
    },
    {
      "timestamp": "2021-03-08T17:16:44.062Z",
      "scenariosCreated": 20,
      "scenariosCompleted": 20,
      "requestsCompleted": 20,
      "latency": {
        "min": 283.8,
        "max": 313.1,
        "median": 293.9,
        "p95": 309.1,
        "p99": 313.1
      },
      "rps": {
        "count": 20,
        "mean": 2
      },
      "scenarioDuration": {
        "min": 285.6,
        "max": 314.9,
        "median": 295.6,
        "p95": 311,
        "p99": 314.9
      },
      "scenarioCounts": {
        "just get hash": 20
      },
      "errors": {},
      "codes": {
        "200": 20
      },
      "matches": 0,
      "latencies": [
        313088219,
        297181161,
        290468156,
        285554490,
        295653872,
        294929685,
        285747891,
        291569328,
        298859865,
        300364722,
        283847478,
        286228368,
        298510763,
        295466033,
        288550339,
        305150062,
        291540224,
        292959266,
        286539198,
        298377380
      ],
      "customStats": {},
      "counters": {},
      "concurrency": 0,
      "pendingRequests": 0,
      "scenariosAvoided": 0
    },
    {
      "timestamp": "2021-03-08T17:16:54.062Z",
      "scenariosCreated": 20,
      "scenariosCompleted": 20,
      "requestsCompleted": 20,
      "latency": {
        "min": 282.9,
        "max": 299,
        "median": 291.7,
        "p95": 298.7,
        "p99": 299
      },
      "rps": {
        "count": 20,
        "mean": 2
      },
      "scenarioDuration": {
        "min": 284.7,
        "max": 300.7,
        "median": 293.6,
        "p95": 300.5,
        "p99": 300.7
      },
      "scenarioCounts": {
        "just get hash": 20
      },
      "errors": {},
      "codes": {
        "200": 20
      },
      "matches": 0,
      "latencies": [
        297331083,
        287596432,
        296296786,
        298406052,
        286264833,
        293677568,
        296470590,
        289130812,
        289113070,
        297630072,
        297508856,
        282868666,
        292354402,
        290043118,
        285415613,
        290905180,
        291017493,
        299011925,
        296274330,
        286601383
      ],
      "customStats": {},
      "counters": {},
      "concurrency": 0,
      "pendingRequests": 0,
      "scenariosAvoided": 0
    },
    {
      "timestamp": "2021-03-08T17:16:54.572Z",
      "scenariosCreated": 1,
      "scenariosCompleted": 1,
      "requestsCompleted": 1,
      "latency": {
        "min": 303.4,
        "max": 303.4,
        "median": 303.4,
        "p95": 303.4,
        "p99": 303.4
      },
      "rps": {
        "count": 1,
        "mean": 2
      },
      "scenarioDuration": {
        "min": 305.8,
        "max": 305.8,
        "median": 305.8,
        "p95": 305.8,
        "p99": 305.8
      },
      "scenarioCounts": {
        "just get hash": 1
      },
      "errors": {},
      "codes": {
        "200": 1
      },
      "matches": 0,
      "latencies": [
        303428933
      ],
      "customStats": {},
      "counters": {},
      "concurrency": 0,
      "pendingRequests": 0,
      "scenariosAvoided": 0
    }
  ]
}